pytact/visualisation_webserver.py
pytact/graph_api_capnp_cython.cpython-311-x86_64-linux-gnu.so
pytact/graph_api.capnp
pytact/graph_api_capnp_cython.cpp
pytact/prover.py
pytact/data_reader.pyx
pytact/fake_coq_client.py
pytact/generate_api.py
pytact/graph_api.capnp.h
pytact/README.md
pytact/py.typed
pytact/graph_api.capnp.cpp
pytact/graph_api_capnp_cython.pxd
pytact/graph_sanity_check.py
pytact/fake_python_server.py
pytact/graph_api_capnp_cython.pyx
pytact/common.py
pytact/data_reader.cpython-311-x86_64-linux-gnu.so
pytact/graph_visualize.py
pytact/oracle_server.py
pytact/data_reader.cpp
pytact/data_reader.pyi
pytact/graph_visualize_browse.py
pytact/__init__.py
pytact/templates/visualizer.html
pytact/templates/capnp_cython.pyx
pytact/templates/capnp_cython.pxd
pytact/scripts/print_tactic_hash.py
pytact/scripts/lemma_distance.py
pytact/scripts/web.py
pytact/scripts/lemma_size.py
pytact/scripts/lemmas_new_tactic.py
pytact/scripts/largest_global_context.py
pytact/scripts/analyze_oracle.py
pytact/scripts/check_axioms.py
pytact/scripts/ssreflect_dependees.py
pytact/scripts/__init__.py
pytact/tests/TestReinforceStdin.v
pytact/tests/prop4.txt
pytact/tests/TestReinforceTcp.v
pytactician.libs/libcapnpc-0-45a51813.10.4.so
pytactician.libs/libcapnp-rpc-0-d46fcc91.10.4.so
pytactician.libs/libcapnp-0-f628859f.10.4.so
pytactician.libs/libkj-async-0-ce734e23.10.4.so
pytactician.libs/libkj-0-abb315d4.10.4.so
datasets/current/add_license.py
pytactician-15.1.dist-info/RECORD
pytactician-15.1.dist-info/top_level.txt
pytactician-15.1.dist-info/entry_points.txt
pytactician-15.1.dist-info/WHEEL
pytactician-15.1.dist-info/LICENSE.md
pytactician-15.1.dist-info/METADATA
