Metadata-Version: 2.1
Name: pytactician
Version: 15.1
Summary: Python Library for interfacing with Coq and Tactician
Author-email: Lasse Blaauwbroek <lasse@blaauwbroek.eu>, Vasily Pestun <vasily.pestun@gmail.com>, Miroslav Olšák <mirek@olsak.net>
License: MIT
Project-URL: Homepage, https://coq-tactician.github.io
Project-URL: Documentation, https://coq-tactician.github.io/api/pytactician-pdoc
Project-URL: Repository, https://github.com/coq-tactician/coq-tactician-api
Project-URL: Changelog, https://github.com/coq-tactician/coq-tactician-api/blob/coq8.11/CHANGELOG.md
Classifier: Development Status :: 5 - Production/Stable
Classifier: Intended Audience :: Science/Research
Classifier: Intended Audience :: Developers
Classifier: License :: OSI Approved :: MIT License
Classifier: Programming Language :: C
Classifier: Programming Language :: Python
Classifier: Programming Language :: Python :: 3
Classifier: Programming Language :: Python :: 3 :: Only
Classifier: Operating System :: POSIX :: Linux
Classifier: Operating System :: MacOS
Classifier: Topic :: Scientific/Engineering
Classifier: Topic :: Scientific/Engineering :: Mathematics
Classifier: Topic :: Scientific/Engineering :: Artificial Intelligence
Requires-Python: >=3.8
License-File: LICENSE.md
Requires-Dist: pycapnp <2,>=1.2.2
Requires-Dist: immutables
Requires-Dist: graphviz
Requires-Dist: sanic ==23.6.0
Requires-Dist: sanic-ext ==23.6.0
Requires-Dist: Jinja2
Requires-Dist: inflection
